Lab1/lab1.srcs/sources_1/new/edge_detector.v
`timescale 1ns / 1ps

module edge_dectector(Signal, Clk, Pe);
    input Signal;
    input Clk;
    output Pe;
    
    reg delaySignal;
    reg delaySignal2;
    reg delaySignal3;
    
    always@(Clk) begin
        delaySignal <= Signal;
        delaySignal2 <= delaySignal;
        delaySignal3 <= delaySignal2;
    end
    
    
    assign Pe = (Signal & ~delaySignal) ^ (delaySignal & ~delaySignal2);

endmodule

Lab1/lab1.srcs/sources_1/new/clock_divider.v
module clock_divider(ClkOut, ClkIn);
    /*output port needs to be a reg because we will drive it with *
     *a behavioral statement*/
    output wire [3:0] ClkOut;
    input wire ClkIn;
    
    /* this is a keyword we have not seen yet!*
     * as the name implies, it is a parameter*
     * that can be changed at compile time...*/
//     parameter n = 5; //make count 6 bits for now
     
//     reg [4:0] Count; //count bit width is based on n! how cool is that!
     
     /*simple behavioral construct to describe a counter...*/
     parameter n = 27;
     
     reg [n:0] Count;
     
     initial 
        Count = 1'b0;
     
     always@(posedge ClkIn) //should look familiar
        Count <= Count + 1;
     
     //Now we need to wire up out ClkOut which is a 4 bit wire
     //Wire up to most significant bits
     assign ClkOut [3:0] = Count[n:n-3];
     
endmodule

Lab1/lab1.srcs/sources_1/new/jackpot.v
`timescale 1ns / 1ps

//module jackpot(LEDS, Clk, SWITCHES, Rst, pe_switch, edg_dect, sum_switch, SlowClk);
module jackpot(LEDS, Clk, SWITCHES, Rst);

    // Declare inputs,output
    output wire [3:0] LEDS;
    input wire [3:0] SWITCHES;
    input wire Clk;
    input wire Rst;
    
    wire [3:0] pe;
    wire [3:0] pe_switch;
    wire edg_dect;
    wire sum_switch;   
    wire SlowClk;
    
    reg [3:0] currentState;
    reg [3:0] nextState;
    
    clock_divider cd2(.ClkOut(SlowClk), .ClkIn(Clk)); 
        
    assign sum_switch = SWITCHES[0] | SWITCHES[1] | SWITCHES[2] | SWITCHES[3]; 
    
    initial currentState = 4'b0001; 
    
    always@(posedge Clk) begin
        if (Rst) 
            currentState <= 4'b0001;
        else 
           case(currentState)
                4'b0001 :
                    if (pe_switch[0])
                        currentState <= 4'b1111;
                    else
                        currentState <= 4'b0010; 
                4'b0010 :
                    if (pe_switch[1])
                        currentState <= 4'b1111;
                    else
                        currentState <= 4'b0100;
                4'b0100 :
                    if (pe_switch[2])
                        currentState <= 4'b1111;
                    else
                        currentState <= 4'b1000;
                4'b1000 :
                    if (pe_switch[3])
                        currentState <= 4'b1111;
                    else
                        currentState <= 4'b0001;
                4'b1111 :
                    if (sum_switch) 
                        currentState <= 4'b1111;
                    else 
                        currentState <= 4'b0001;
            endcase
    end 
     
    
    edge_dectector edge0(SWITCHES[0], Clk, pe_switch[0]);
    edge_dectector edge1(SWITCHES[1], Clk, pe_switch[1]);
    edge_dectector edge2(SWITCHES[2], Clk, pe_switch[2]);
    edge_dectector edge3(SWITCHES[3], Clk, pe_switch[3]);

    
    assign edg_dect = pe_switch[0] || pe_switch[1] || pe_switch[2] || pe_switch[3];
    
    assign LEDS = currentState;    
    
endmodule

Lab1/lab1.srcs/sim_1/new/jackpot_tb.v
/********************************************************************
 *
 * Andrew Douglass
 * August 23, 2018
 * jackpot_tb.v
 *
 *******************************************************************/

`timescale 1ns / 1ps

// ENSURE THE FILE NAME BELOW MATCHES YOURS
//`include "jackpot.v"

module jackpot_tb;

// Inputs to the DUT
reg Clk;
reg Rst;
reg [3:0] switches;
// Output from the DUT
wire [3:0] leds;
wire [3:0] pe_switch;
wire edg_dect;
wire sum_switch;

// Init the DUT by connecting the ports
jackpot jkpot01 (
  .Clk(Clk),
  .Rst(Rst),
  .SWITCHES(switches),
  .LEDS(leds),
  .pe_switch(pe_switch),
  .edg_dect(edg_dect),
  .sum_switch(sum_switch)
);

initial begin
  // Print the counter activity to the console
  $monitor("time=%d, Rst=%d, switches=%b, leds=%b", $time, Rst, switches, leds);

  $dumpfile("JackpotWave.vcd");   // Output the signals to the waveform file
  $dumpvars(0, jackpot_tb);       // Dump signals in the top module

  // Default starting value for all input signals
  Clk = 1'b0;
  Rst = 1'b1;
  switches = 4'b0000;

  // Exercise the inputs to test the module
  #10000;
  Rst = 1'b0;
  #100000;
  @(posedge leds[1]);
      switches = 4'b0010;
  #100000;
  Rst = 1'b1;
  #100000;
  Rst = 1'b0;
  #10000;
  @(posedge leds[3]);
    switches = 4'b1000;
  #500000;
  $finish;

end

// Generate a 50% duty cycle clock with a period of 8ns.
// This is a 125MHz clock
always
  #20000 Clk <= ~Clk;

endmodule

Lab1/lab1.sim/sim_1/behav/xsim/JackpotWave.vcd
$date
   Tue Jan 31 21:39:20 2023
$end
$version
  2022.2
$end
$timescale
  1ps
$end
$scope module jackpot_tb $end
$var reg 1 ! Clk $end
$var reg 1 " Rst $end
$var reg 4 # switches [3:0] $end
$var wire 4 $ leds [3:0] $end
$var wire 4 % pe_switch [3:0] $end
$var wire 1 & edg_dect $end
$var wire 1 ' sum_switch $end
$scope module jkpot01 $end
$var wire 4 $ LEDS [3:0] $end
$var wire 4 ( SWITCHES [3:0] $end
$var wire 1 ) Clk $end
$var wire 1 * Rst $end
$var wire 4 % pe_switch [3:0] $end
$var wire 1 & edg_dect $end
$var wire 1 ' sum_switch $end
$var wire 1 + SlowClk $end
$var reg 4 , currentState [3:0] $end
$var reg 4 - nextState [3:0] $end
$scope module cd2 $end
$var wire 4 . ClkOut [3:0] $end
$var wire 1 ) ClkIn $end
$var reg 28 / Count [27:0] $end
$upscope $end
$scope module edge0 $end
$var wire 1 0 Signal $end
$var wire 1 ) Clk $end
$var wire 1 1 Pe $end
$var reg 1 2 delaySignal $end
$var reg 1 3 delaySignal2 $end
$var reg 1 4 delaySignal3 $end
$upscope $end
$scope module edge1 $end
$var wire 1 5 Signal $end
$var wire 1 ) Clk $end
$var wire 1 6 Pe $end
$var reg 1 7 delaySignal $end
$var reg 1 8 delaySignal2 $end
$var reg 1 9 delaySignal3 $end
$upscope $end
$scope module edge2 $end
$var wire 1 : Signal $end
$var wire 1 ) Clk $end
$var wire 1 ; Pe $end
$var reg 1 < delaySignal $end
$var reg 1 = delaySignal2 $end
$var reg 1 > delaySignal3 $end
$upscope $end
$scope module edge3 $end
$var wire 1 ? Signal $end
$var wire 1 ) Clk $end
$var wire 1 @ Pe $end
$var reg 1 A delaySignal $end
$var reg 1 B delaySignal2 $end
$var reg 1 C delaySignal3 $end
$upscope $end
$upscope $end
$upscope $end
$enddefinitions $end
#0
$dumpvars
0!
1"
b0 #
b1 $
b0 %
0&
0'
b0 (
0)
1*
0+
b1 ,
bx -
b0 .
b0 /
00
01
02
x3
x4
05
06
07
x8
x9
0:
0;
0<
x=
x>
0?
0@
0A
xB
xC
$end
#10000000
0"
0*
#20000000
1!
b10 $
b0 %
1)
b10 ,
b1 /
01
03
06
08
0;
0=
0@
0B
#40000000
0!
0)
04
09
0>
0C
#60000000
1!
b100 $
1)
b100 ,
b10 /
#80000000
0!
0)
#100000000
1!
b1000 $
1)
b1000 ,
b11 /
#120000000
0!
0)
#140000000
1!
b1 $
1)
b1 ,
b100 /
#160000000
0!
0)
#180000000
1!
b10 #
b10 $
b10 %
1&
1'
b10 (
1)
b10 ,
b101 /
00
15
16
0:
0?
#200000000
0!
b10 %
0)
16
17
#220000000
1!
b1111 $
b0 %
0&
1)
b1111 ,
b110 /
06
18
#240000000
0!
0)
19
#260000000
1!
1)
b1111 ,
b111 /
#280000000
0!
1"
0)
1*
#300000000
1!
b1 $
1)
b1 ,
b1000 /
#320000000
0!
0)
#340000000
1!
1)
b1 ,
b1001 /
#360000000
0!
0)
#380000000
1!
0"
b10 $
1)
0*
b10 ,
b1010 /
#400000000
0!
0)
#420000000
1!
b100 $
1)
b100 ,
b1011 /
#440000000
0!
0)
#460000000
1!
b1000 #
b1000 $
b1000 %
1&
b1000 (
1)
b1000 ,
b1100 /
00
05
06
0:
1?
1@
#480000000
0!
b1000 %
0)
06
07
1@
1A
#500000000
1!
b1111 $
b0 %
0&
1)
b1111 ,
b1101 /
06
08
0@
1B
#520000000
0!
0)
09
1C
#540000000
1!
1)
b1111 ,
b1110 /
#560000000
0!
0)
#580000000
1!
1)
b1111 ,
b1111 /
#600000000
0!
0)
#620000000
1!
1)
b1111 ,
b10000 /
#640000000
0!
0)
#660000000
1!
1)
b1111 ,
b10001 /
#680000000
0!
0)
#700000000
1!
1)
b1111 ,
b10010 /
#720000000
0!
0)
#740000000
1!
1)
b1111 ,
b10011 /
#760000000
0!
0)
#780000000
1!
1)
b1111 ,
b10100 /
#800000000
0!
0)
#820000000
1!
1)
b1111 ,
b10101 /
#840000000
0!
0)
#860000000
1!
1)
b1111 ,
b10110 /
#880000000
0!
0)
#900000000
1!
1)
b1111 ,
b10111 /
#920000000
0!
0)
#940000000
1!
1)
b1111 ,
b11000 /
